george/__init__.py
george/george_version.py
george/gp.py
george/kernel_interface.cpp
george/kernel_interface.cpython-313-x86_64-linux-gnu.so
george/kernels.py
george/metrics.py
george/modeling.py
george/utils.py
george/include/george/exceptions.h
george/include/george/george.h
george/include/george/hodlr.h
george/include/george/kernels.h
george/include/george/metrics.h
george/include/george/parser.h
george/include/george/subspace.h
george/solvers/__init__.py
george/solvers/_hodlr.cpp
george/solvers/_hodlr.cpython-313-x86_64-linux-gnu.so
george/solvers/basic.py
george/solvers/hodlr.py
george/solvers/trivial.py
george-0.4.4.dist-info/METADATA
george-0.4.4.dist-info/WHEEL
george-0.4.4.dist-info/RECORD
george-0.4.4.dist-info/licenses/AUTHORS.rst
george-0.4.4.dist-info/licenses/LICENSE
