Metadata-Version: 2.1
Name: george
Version: 0.4.4
Summary: Blazingly fast Gaussian Processes for regression.
Author-Email: Daniel Foreman-Mackey <foreman.mackey@gmail.com>
License: Copyright (c) 2012-2021 Daniel Foreman-Mackey and contributors
Project-URL: Homepage, https://github.com/dfm/george
Requires-Python: >=3.9
Requires-Dist: numpy
Requires-Dist: scipy
